dash_colorful/DashColorful.py
dash_colorful/__init__.py
dash_colorful/_imports_.py
dash_colorful/dash-colorful.css
dash_colorful/dash_colorful.js
dash_colorful/metadata.json
dash_colorful/package-info.json
dash_colorful-0.1.0.dist-info/LICENSE
dash_colorful-0.1.0.dist-info/METADATA
dash_colorful-0.1.0.dist-info/WHEEL
dash_colorful-0.1.0.dist-info/top_level.txt
dash_colorful-0.1.0.dist-info/RECORD
