Metadata-Version: 2.1
Name: dash-colorful
Version: 0.1.0
Summary: Color picker for Dash created with react-colorful
Author: Philippe Duval <philippe@plot.ly>
License: MIT
Platform: UNKNOWN
Classifier: Framework :: Dash
License-File: LICENSE
